ease-image-processing/__init__.py
ease-image-processing/structure/__init__.py
ease-image-processing/structure/combination.py
ease-image-processing/structure/transformation.py
ease-image-processing/utils/__init__.py
ease-image-processing/utils/graphics.py
ease-image-processing/utils/io.py
easeimage/__init__.py
easeimage/structure/__init__.py
easeimage/structure/combination.py
easeimage/structure/transformation.py
easeimage/utils/__init__.py
easeimage/utils/graphics.py
easeimage/utils/io.py
image-processing/__init__.py
image-processing/structure/__init__.py
image-processing/structure/combination.py
image-processing/structure/transformation.py
image-processing/utils/__init__.py
image-processing/utils/graphics.py
image-processing/utils/io.py
ease_image_processing-0.0.4.dist-info/METADATA
ease_image_processing-0.0.4.dist-info/WHEEL
ease_image_processing-0.0.4.dist-info/top_level.txt
ease_image_processing-0.0.4.dist-info/RECORD
