Metadata-Version: 2.1
Name: ease-image-processing
Version: 0.0.4
Summary: A wrapper of scikit image for ease of use
Home-page: https://github.com/VitorBSP/ease-image-processing
Author: =?utf-8?q?V=C3=ADtor_Pereira?=
Author-email: vitorpereira3115@gmail.com
Requires-Python: >=3.8
Requires-Dist: matplotlib
Requires-Dist: seaborn
Requires-Dist: numpy
Requires-Dist: scikit-image (>=0.16.1)
